prompt_as
