Metadata-Version: 2.1
Name: prompt-as
Version: 0.2.0
Summary: GPT
Home-page: https://github.com/Upsonic/prompt-as-function
Author: Upsonic
Author-email: onur@upsonic.co
License: MIT
Platform: UNKNOWN
Requires-Python: >= 3.9
